breactsdk/__init__.py
breactsdk/client.py
breactsdk/config.py
breactsdk-0.1.5.dist-info/METADATA
breactsdk-0.1.5.dist-info/WHEEL
breactsdk-0.1.5.dist-info/top_level.txt
breactsdk-0.1.5.dist-info/RECORD
